{
  "generated_at": "2026-05-24 02:02:27",
  "total_processed": 20,
  "stop_reason": "遇到比赛时间超出未来2小时: 504900",
  "simulation_params": {
    "n_sims": 500000,
    "max_goals": 5
  },
  "records": [
    {
      "match_id": "505521",
      "时间": "2026-05-24 01:55:00",
      "赛事": "乌拉圭甲组联赛",
      "主队": "切洛拉高",
      "客队": "波士顿河",
      "胜概率": "39.67%",
      "平概率": "27.76%",
      "负概率": "32.57%",
      "主进球": "1.251",
      "客进球": "1.106",
      "胜赔付": "0.8450",
      "平赔付": "0.8273",
      "负赔付": "0.8728",
      "平均赔付": "0.8488",
      "轮次>10%": "1, 2, 3, 4",
      "记录时间": "2026-05-24 02:01:00"
    },
    {
      "match_id": "504312",
      "时间": "2026-05-24 02:00:00",
      "赛事": "德国杯",
      "主队": "拜仁慕尼黑",
      "客队": "史特加",
      "胜概率": "70.99%",
      "平概率": "15.48%",
      "负概率": "13.54%",
      "主进球": "2.646",
      "客进球": "1.136",
      "胜赔付": "0.9086",
      "平赔付": "0.8514",
      "负赔付": "0.8121",
      "平均赔付": "0.8852",
      "轮次>10%": "2, 3, 4, 5, 6",
      "记录时间": "2026-05-24 02:01:04"
    },
    {
      "match_id": "505989",
      "时间": "2026-05-24 02:45:00",
      "赛事": "意大利甲组联赛",
      "主队": "拉素",
      "客队": "比萨",
      "胜概率": "62.33%",
      "平概率": "20.79%",
      "负概率": "16.88%",
      "主进球": "1.960",
      "客进球": "0.922",
      "胜赔付": "1.0222",
      "平赔付": "0.8316",
      "负赔付": "0.6753",
      "平均赔付": "0.9011",
      "轮次>10%": "1, 2, 3, 4",
      "记录时间": "2026-05-24 02:01:09"
    },
    {
      "match_id": "504870",
      "时间": "2026-05-24 02:45:00",
      "赛事": "比利时甲组联赛",
      "主队": "安特卫普",
      "客队": "韦斯达路",
      "胜概率": "48.83%",
      "平概率": "22.37%",
      "负概率": "28.79%",
      "主进球": "1.862",
      "客进球": "1.405",
      "胜赔付": "0.9474",
      "平赔付": "0.8055",
      "负赔付": "0.8753",
      "平均赔付": "0.8911",
      "轮次>10%": "1, 2, 3, 4, 5",
      "记录时间": "2026-05-24 02:01:13"
    },
    {
      "match_id": "504871",
      "时间": "2026-05-24 02:45:00",
      "赛事": "比利时甲组联赛",
      "主队": "标准列治",
      "客队": "查内尔",
      "胜概率": "47.53%",
      "平概率": "25.20%",
      "负概率": "27.27%",
      "主进球": "1.537",
      "客进球": "1.109",
      "胜赔付": "0.9791",
      "平赔付": "0.8316",
      "负赔付": "0.8181",
      "平均赔付": "0.8914",
      "轮次>10%": "1, 2, 3, 4",
      "记录时间": "2026-05-24 02:01:18"
    },
    {
      "match_id": "504872",
      "时间": "2026-05-24 02:45:00",
      "赛事": "比利时甲组联赛",
      "主队": "奥特希费利",
      "客队": "亨克",
      "胜概率": "28.19%",
      "平概率": "23.32%",
      "负概率": "48.48%",
      "主进球": "1.287",
      "客进球": "1.739",
      "胜赔付": "1.0996",
      "平赔付": "0.8163",
      "负赔付": "0.8242",
      "平均赔付": "0.8847",
      "轮次>10%": "1, 2, 3, 4, 5",
      "记录时间": "2026-05-24 02:01:23"
    },
    {
      "match_id": "504899",
      "时间": "2026-05-24 02:45:00",
      "赛事": "美国职业大联盟联赛",
      "主队": "圣路易斯城SC",
      "客队": "奥斯汀FC",
      "胜概率": "57.76%",
      "平概率": "21.14%",
      "负概率": "21.10%",
      "主进球": "1.988",
      "客进球": "1.139",
      "胜赔付": "0.9299",
      "平赔付": "0.8310",
      "负赔付": "0.8545",
      "平均赔付": "0.8909",
      "轮次>10%": "1, 2, 3, 4, 5",
      "记录时间": "2026-05-24 02:01:27"
    },
    {
      "match_id": "505358",
      "时间": "2026-05-24 03:00:00",
      "赛事": "西班牙甲组联赛",
      "主队": "艾拉维斯",
      "客队": "华历简奴",
      "胜概率": "41.95%",
      "平概率": "25.74%",
      "负概率": "32.32%",
      "主进球": "1.433",
      "客进球": "1.229",
      "胜赔付": "0.9228",
      "平赔付": "0.8236",
      "负赔付": "0.9533",
      "平均赔付": "0.9041",
      "轮次>10%": "1, 2, 3, 4",
      "记录时间": "2026-05-24 02:01:32"
    },
    {
      "match_id": "505359",
      "时间": "2026-05-24 03:00:00",
      "赛事": "西班牙甲组联赛",
      "主队": "贝迪斯",
      "客队": "利云特",
      "胜概率": "41.65%",
      "平概率": "23.08%",
      "负概率": "35.26%",
      "主进球": "1.681",
      "客进球": "1.534",
      "胜赔付": "0.9414",
      "平赔付": "0.8102",
      "负赔付": "0.9169",
      "平均赔付": "0.8993",
      "轮次>10%": "1, 2, 3, 4, 5",
      "记录时间": "2026-05-24 02:01:37"
    },
    {
      "match_id": "505360",
      "时间": "2026-05-24 03:00:00",
      "赛事": "西班牙甲组联赛",
      "主队": "切尔达",
      "客队": "西维尔",
      "胜概率": "56.34%",
      "平概率": "23.34%",
      "负概率": "20.32%",
      "主进球": "1.751",
      "客进球": "0.961",
      "胜赔付": "1.0367",
      "平赔付": "0.7702",
      "负赔付": "0.7619",
      "平均赔付": "0.8983",
      "轮次>10%": "1, 2, 3, 4",
      "记录时间": "2026-05-24 02:01:41"
    },
    {
      "match_id": "505361",
      "时间": "2026-05-24 03:00:00",
      "赛事": "西班牙甲组联赛",
      "主队": "爱斯宾奴",
      "客队": "皇家苏斯达",
      "胜概率": "42.17%",
      "平概率": "24.93%",
      "负概率": "32.90%",
      "主进球": "1.492",
      "客进球": "1.297",
      "胜赔付": "0.9025",
      "平赔付": "0.8501",
      "负赔付": "0.9211",
      "平均赔付": "0.8947",
      "轮次>10%": "1, 2, 3, 4",
      "记录时间": "2026-05-24 02:01:46"
    },
    {
      "match_id": "505362",
      "时间": "2026-05-24 03:00:00",
      "赛事": "西班牙甲组联赛",
      "主队": "加泰",
      "客队": "奥沙辛拿",
      "胜概率": "37.10%",
      "平概率": "29.29%",
      "负概率": "33.61%",
      "主进球": "1.125",
      "客进球": "1.058",
      "胜赔付": "0.9646",
      "平赔付": "0.7968",
      "负赔付": "0.9410",
      "平均赔付": "0.9014",
      "轮次>10%": "0, 1, 2, 3, 4",
      "记录时间": "2026-05-24 02:01:50"
    },
    {
      "match_id": "505363",
      "时间": "2026-05-24 03:00:00",
      "赛事": "西班牙甲组联赛",
      "主队": "马略卡",
      "客队": "奥维多",
      "胜概率": "64.45%",
      "平概率": "20.89%",
      "负概率": "14.67%",
      "主进球": "1.928",
      "客进球": "0.805",
      "胜赔付": "0.9023",
      "平赔付": "0.8876",
      "负赔付": "0.8946",
      "平均赔付": "0.8981",
      "轮次>10%": "1, 2, 3, 4",
      "记录时间": "2026-05-24 02:01:55"
    },
    {
      "match_id": "505364",
      "时间": "2026-05-24 03:00:00",
      "赛事": "西班牙甲组联赛",
      "主队": "皇家马德里",
      "客队": "毕尔包",
      "胜概率": "63.69%",
      "平概率": "19.13%",
      "负概率": "17.18%",
      "主进球": "2.194",
      "客进球": "1.070",
      "胜赔付": "0.8916",
      "平赔付": "0.8801",
      "负赔付": "0.9448",
      "平均赔付": "0.8981",
      "轮次>10%": "1, 2, 3, 4, 5",
      "记录时间": "2026-05-24 02:02:00"
    },
    {
      "match_id": "505365",
      "时间": "2026-05-24 03:00:00",
      "赛事": "西班牙甲组联赛",
      "主队": "华伦西亚",
      "客队": "巴塞隆拿",
      "胜概率": "28.21%",
      "平概率": "21.76%",
      "负概率": "50.03%",
      "主进球": "1.434",
      "客进球": "1.943",
      "胜赔付": "0.8492",
      "平赔付": "0.8094",
      "负赔付": "0.9706",
      "平均赔付": "0.8957",
      "轮次>10%": "1, 2, 3, 4, 5",
      "记录时间": "2026-05-24 02:02:04"
    },
    {
      "match_id": "505366",
      "时间": "2026-05-24 03:00:00",
      "赛事": "西班牙甲组联赛",
      "主队": "杰罗纳",
      "客队": "艾尔切",
      "胜概率": "52.39%",
      "平概率": "22.69%",
      "负概率": "24.92%",
      "主进球": "1.825",
      "客进球": "1.208",
      "胜赔付": "0.9431",
      "平赔付": "0.8282",
      "负赔付": "0.8846",
      "平均赔付": "0.8999",
      "轮次>10%": "1, 2, 3, 4, 5",
      "记录时间": "2026-05-24 02:02:09"
    },
    {
      "match_id": "504950",
      "时间": "2026-05-24 03:00:00",
      "赛事": "智利甲组联赛",
      "主队": "纽柏莱斯",
      "客队": "康塞普森大学",
      "胜概率": "50.13%",
      "平概率": "26.27%",
      "负概率": "23.61%",
      "主进球": "1.473",
      "客进球": "0.931",
      "胜赔付": "0.8020",
      "平赔付": "0.9324",
      "负赔付": "1.0861",
      "平均赔付": "0.8896",
      "轮次>10%": "1, 2, 3, 4",
      "记录时间": "2026-05-24 02:02:13"
    },
    {
      "match_id": "504928",
      "时间": "2026-05-24 04:00:00",
      "赛事": "巴西甲组联赛",
      "主队": "圣保罗",
      "客队": "保地花高",
      "胜概率": "50.24%",
      "平概率": "24.28%",
      "负概率": "25.48%",
      "主进球": "1.648",
      "客进球": "1.109",
      "胜赔付": "0.8540",
      "平赔付": "0.8742",
      "负赔付": "0.9810",
      "平均赔付": "0.8883",
      "轮次>10%": "1, 2, 3, 4",
      "记录时间": "2026-05-24 02:02:18"
    },
    {
      "match_id": "504929",
      "时间": "2026-05-24 04:00:00",
      "赛事": "巴西甲组联赛",
      "主队": "维多利亚",
      "客队": "国际体育会",
      "胜概率": "34.25%",
      "平概率": "27.21%",
      "负概率": "38.54%",
      "主进球": "1.171",
      "客进球": "1.264",
      "胜赔付": "0.9350",
      "平赔付": "0.8436",
      "负赔付": "0.8863",
      "平均赔付": "0.8899",
      "轮次>10%": "1, 2, 3, 4",
      "记录时间": "2026-05-24 02:02:22"
    },
    {
      "match_id": "505441",
      "时间": "2026-05-24 04:00:00",
      "赛事": "美国国家女子联赛",
      "主队": "路易维尔竞赛女足",
      "客队": "北卡罗勇气女足",
      "胜概率": "27.93%",
      "平概率": "23.77%",
      "负概率": "48.30%",
      "主进球": "1.240",
      "客进球": "1.685",
      "胜赔付": "0.8294",
      "平赔付": "0.7558",
      "负赔付": "0.9178",
      "平均赔付": "0.8493",
      "轮次>10%": "1, 2, 3, 4",
      "记录时间": "2026-05-24 02:02:27"
    }
  ]
}