{
  "generated_at": "2026-05-31 11:01:54",
  "total_processed": 13,
  "stop_reason": "遇到比赛时间超出未来2小时: 505541",
  "simulation_params": {
    "n_sims": 500000,
    "max_goals": 5
  },
  "records": [
    {
      "match_id": "506124",
      "时间": "2026-05-31 10:00:00",
      "赛事": "国际友谊赛",
      "主队": "墨西哥",
      "客队": "澳洲",
      "胜概率": "57.28%",
      "平概率": "23.28%",
      "负概率": "19.45%",
      "主进球": "1.726",
      "客进球": "0.913",
      "胜赔付": "0.9909",
      "平赔付": "0.7681",
      "负赔付": "0.7779",
      "平均赔付": "0.8841",
      "轮次>10%": "0:7.1% 1:19.0% 2:24.8% 3:21.7% 4:14.2% 5:8.0% 6:3.5% 7+:1.7%",
      "记录时间": "2026-05-31 11:00:56"
    },
    {
      "match_id": "505738",
      "时间": "2026-05-31 10:00:00",
      "赛事": "美国冠军联赛",
      "主队": "蒙特雷湾",
      "客队": "劳顿联",
      "胜概率": "38.02%",
      "平概率": "25.18%",
      "负概率": "36.80%",
      "主进球": "1.412",
      "客进球": "1.387",
      "胜赔付": "0.8364",
      "平赔付": "0.8235",
      "负赔付": "0.8832",
      "平均赔付": "0.8496",
      "轮次>10%": "0:6.2% 1:17.2% 2:23.7% 3:22.1% 4:15.2% 5:8.8% 6:4.3% 7+:2.4%",
      "记录时间": "2026-05-31 11:01:00"
    },
    {
      "match_id": "505739",
      "时间": "2026-05-31 10:30:00",
      "赛事": "美国冠军联赛",
      "主队": "拉斯维加斯灯火",
      "客队": "FC陶沙",
      "胜概率": "37.75%",
      "平概率": "26.23%",
      "负概率": "36.02%",
      "主进球": "1.317",
      "客进球": "1.284",
      "胜赔付": "0.8304",
      "平赔付": "0.8132",
      "负赔付": "0.9005",
      "平均赔付": "0.8495",
      "轮次>10%": "0:7.6% 1:19.5% 2:25.0% 3:21.5% 4:13.8% 5:7.5% 6:3.4% 7+:1.8%",
      "记录时间": "2026-05-31 11:01:05"
    },
    {
      "match_id": "505740",
      "时间": "2026-05-31 10:30:00",
      "赛事": "美国冠军联赛",
      "主队": "凤凰城展翅",
      "客队": "萨克拉门托共和",
      "胜概率": "34.06%",
      "平概率": "27.60%",
      "负概率": "38.34%",
      "主进球": "1.151",
      "客进球": "1.243",
      "胜赔付": "0.8446",
      "平赔付": "0.8364",
      "负赔付": "0.8626",
      "平均赔付": "0.8491",
      "轮次>10%": "0:9.5% 1:22.2% 2:25.9% 3:20.1% 4:12.0% 5:6.2% 6:2.7% 7+:1.4%",
      "记录时间": "2026-05-31 11:01:10"
    },
    {
      "match_id": "506238",
      "时间": "2026-05-31 13:00:00",
      "赛事": "日本J1百年构想联赛",
      "主队": "清水心跳",
      "客队": "横滨水手",
      "胜概率": "39.45%",
      "平概率": "26.68%",
      "负概率": "33.87%",
      "主进球": "1.323",
      "客进球": "1.206",
      "胜赔付": "0.9271",
      "平赔付": "0.8830",
      "负赔付": "0.8806",
      "平均赔付": "0.8991",
      "轮次>10%": "0:8.3% 1:20.5% 2:25.4% 3:20.9% 4:13.1% 5:7.0% 6:3.2% 7+:1.7%",
      "记录时间": "2026-05-31 11:01:15"
    },
    {
      "match_id": "506239",
      "时间": "2026-05-31 13:00:00",
      "赛事": "日本J1百年构想联赛",
      "主队": "冈山绿雉",
      "客队": "浦和红钻",
      "胜概率": "32.92%",
      "平概率": "27.55%",
      "负概率": "39.53%",
      "主进球": "1.122",
      "客进球": "1.267",
      "胜赔付": "0.9548",
      "平赔付": "0.8348",
      "负赔付": "0.9012",
      "平均赔付": "0.8981",
      "轮次>10%": "0:9.6% 1:22.4% 2:25.9% 3:19.9% 4:11.7% 5:6.2% 6:2.8% 7+:1.4%",
      "记录时间": "2026-05-31 11:01:20"
    },
    {
      "match_id": "506265",
      "时间": "2026-05-31 13:00:00",
      "赛事": "日本J2/J3百年构想联赛",
      "主队": "秋田蓝闪电",
      "客队": "北海道札幌冈萨多",
      "胜概率": "41.15%",
      "平概率": "26.17%",
      "负概率": "32.68%",
      "主进球": "1.388",
      "客进球": "1.211",
      "胜赔付": "0.8930",
      "平赔付": "0.8530",
      "负赔付": "0.9184",
      "平均赔付": "0.8901",
      "轮次>10%": "0:7.7% 1:19.6% 2:25.0% 3:21.2% 4:13.6% 5:7.5% 6:3.5% 7+:1.9%",
      "记录时间": "2026-05-31 11:01:25"
    },
    {
      "match_id": "506266",
      "时间": "2026-05-31 13:00:00",
      "赛事": "日本J2/J3百年构想联赛",
      "主队": "群马温泉",
      "客队": "FC岐阜",
      "胜概率": "37.10%",
      "平概率": "26.17%",
      "负概率": "36.73%",
      "主进球": "1.304",
      "客进球": "1.299",
      "胜赔付": "0.8978",
      "平赔付": "0.8715",
      "负赔付": "0.8999",
      "平均赔付": "0.8915",
      "轮次>10%": "0:7.6% 1:19.4% 2:25.0% 3:21.4% 4:13.7% 5:7.5% 6:3.5% 7+:1.8%",
      "记录时间": "2026-05-31 11:01:30"
    },
    {
      "match_id": "506267",
      "时间": "2026-05-31 13:00:00",
      "赛事": "日本J2/J3百年构想联赛",
      "主队": "金泽萨维根",
      "客队": "鸟取飞翔",
      "胜概率": "49.34%",
      "平概率": "26.59%",
      "负概率": "24.07%",
      "主进球": "1.434",
      "客进球": "0.918",
      "胜赔付": "0.9424",
      "平赔付": "0.8322",
      "负赔付": "0.8497",
      "平均赔付": "0.8878",
      "轮次>10%": "0:9.9% 1:22.6% 2:26.2% 3:20.0% 4:11.6% 5:6.0% 6:2.5% 7+:1.1%",
      "记录时间": "2026-05-31 11:01:34"
    },
    {
      "match_id": "506268",
      "时间": "2026-05-31 13:00:00",
      "赛事": "日本J2/J3百年构想联赛",
      "主队": "山形山神",
      "客队": "松本山雅",
      "胜概率": "42.33%",
      "平概率": "25.81%",
      "负概率": "31.87%",
      "主进球": "1.433",
      "客进球": "1.211",
      "胜赔付": "0.8804",
      "平赔付": "0.8594",
      "负赔付": "0.9274",
      "平均赔付": "0.8891",
      "轮次>10%": "0:7.4% 1:19.1% 2:24.7% 3:21.3% 4:14.1% 5:7.9% 6:3.7% 7+:2.0%",
      "记录时间": "2026-05-31 11:01:39"
    },
    {
      "match_id": "506269",
      "时间": "2026-05-31 13:00:00",
      "赛事": "日本J2/J3百年构想联赛",
      "主队": "FC今治",
      "客队": "FC琉球",
      "胜概率": "57.74%",
      "平概率": "23.65%",
      "负概率": "18.61%",
      "主进球": "1.678",
      "客进球": "0.842",
      "胜赔付": "0.9411",
      "平赔付": "0.8324",
      "负赔付": "0.8190",
      "平均赔付": "0.8890",
      "轮次>10%": "0:8.3% 1:20.5% 2:25.3% 3:20.9% 4:13.2% 5:7.2% 6:3.1% 7+:1.4%",
      "记录时间": "2026-05-31 11:01:44"
    },
    {
      "match_id": "506270",
      "时间": "2026-05-31 13:00:00",
      "赛事": "日本J2/J3百年构想联赛",
      "主队": "枥木SC",
      "客队": "长野帕塞罗",
      "胜概率": "58.15%",
      "平概率": "22.62%",
      "负概率": "19.23%",
      "主进球": "1.802",
      "客进球": "0.943",
      "胜赔付": "0.9188",
      "平赔付": "0.8528",
      "负赔付": "0.8460",
      "平均赔付": "0.8885",
      "轮次>10%": "0:6.4% 1:17.7% 2:24.1% 3:22.0% 4:14.9% 5:8.8% 6:4.1% 7+:1.9%",
      "记录时间": "2026-05-31 11:01:49"
    },
    {
      "match_id": "506271",
      "时间": "2026-05-31 13:00:00",
      "赛事": "日本J2/J3百年构想联赛",
      "主队": "赞岐卡马达马尼",
      "客队": "北九州向日葵",
      "胜概率": "35.98%",
      "平概率": "26.99%",
      "负概率": "37.04%",
      "主进球": "1.237",
      "客进球": "1.258",
      "胜赔付": "0.8994",
      "平赔付": "0.8716",
      "负赔付": "0.8926",
      "平均赔付": "0.8893",
      "轮次>10%": "0:8.8% 1:21.1% 2:25.4% 3:20.3% 4:12.6% 5:6.9% 6:3.2% 7+:1.7%",
      "记录时间": "2026-05-31 11:01:54"
    }
  ]
}